<annotation>
	<folder>train</folder>
	<filename>dog.35.jpg</filename>
	<path>D:\object_detection_demo-master\data\images\train\dog.35.jpg</path>
	<source>
		<database>Unknown</database>
	</source>
	<size>
		<width>800</width>
		<height>600</height>
		<depth>3</depth>
	</size>
	<segmented>0</segmented>
	<object>
		<name>dog</name>
		<pose>Unspecified</pose>
		<truncated>0</truncated>
		<difficult>0</difficult>
		<bndbox>
			<xmin>99</xmin>
			<ymin>221</ymin>
			<xmax>322</xmax>
			<ymax>444</ymax>
		</bndbox>
	</object>
	<object>
		<name>dog</name>
		<pose>Unspecified</pose>
		<truncated>0</truncated>
		<difficult>0</difficult>
		<bndbox>
			<xmin>561</xmin>
			<ymin>180</ymin>
			<xmax>759</xmax>
			<ymax>355</ymax>
		</bndbox>
	</object>
</annotation>
