<annotation>
	<folder>train</folder>
	<filename>raccoon.196.jpg</filename>
	<path>D:\object_detection_demo-master\data\images\train\raccoon.196.jpg</path>
	<source>
		<database>Unknown</database>
	</source>
	<size>
		<width>800</width>
		<height>600</height>
		<depth>3</depth>
	</size>
	<segmented>0</segmented>
	<object>
		<name>raccoon</name>
		<pose>Unspecified</pose>
		<truncated>1</truncated>
		<difficult>0</difficult>
		<bndbox>
			<xmin>635</xmin>
			<ymin>325</ymin>
			<xmax>800</xmax>
			<ymax>535</ymax>
		</bndbox>
	</object>
	<object>
		<name>raccoon</name>
		<pose>Unspecified</pose>
		<truncated>0</truncated>
		<difficult>0</difficult>
		<bndbox>
			<xmin>431</xmin>
			<ymin>401</ymin>
			<xmax>654</xmax>
			<ymax>595</ymax>
		</bndbox>
	</object>
</annotation>
